qtdark
