Metadata-Version: 1.0
Name: qtdark
Version: 0.1.4
Summary: Create QtDark project.
Home-page: https://github.com/nguyenvantat1182002/SeleneXtra
Author: Tat Nguyen Van
Author-email: nguyenvantat1182002@gmail.com
License: UNKNOWN
Platform: UNKNOWN
